mockitup/__init__.py
mockitup/actions.py
mockitup/arguments_matcher.py
mockitup/composer.py
mockitup/proxies.py
mockitup-1.1.0.dist-info/LICENSE
mockitup-1.1.0.dist-info/METADATA
mockitup-1.1.0.dist-info/WHEEL
mockitup-1.1.0.dist-info/top_level.txt
mockitup-1.1.0.dist-info/RECORD
