Metadata-Version: 2.1
Name: mockitup
Version: 1.1.0
Summary: A `unittest.mock` wrapper for easier mocking
Author-email: Shacham Ginat <shacham6@gmail.com>
License: MIT License
Requires-Python: <4.0,>=3.8.1
License-File: LICENSE
Requires-Dist: PyHamcrest >=2.0.2
Requires-Dist: typing-extensions >=3.10.0
